ActiveRecord/__init__.py
active_record_mc-0.7.1.dist-info/LICENSE
active_record_mc-0.7.1.dist-info/METADATA
active_record_mc-0.7.1.dist-info/WHEEL
active_record_mc-0.7.1.dist-info/RECORD
