Metadata-Version: 2.1
Name: active-record-mc
Version: 0.7.1
Summary: Simple ORM for basic operations in SQLite databases
License: MIT
Author: Chris Brown
Author-email: chris@marcrisoft.co.uk
Requires-Python: >=3.8,<4.0
Classifier: Development Status :: 4 - Beta
Classifier: Intended Audience :: End Users/Desktop
Classifier: License :: OSI Approved :: MIT License
Classifier: Programming Language :: Python :: 3
Classifier: Programming Language :: Python :: 3.8
Classifier: Programming Language :: Python :: 3.9
Classifier: Programming Language :: Python :: 3.10
Classifier: Programming Language :: Python :: 3.11
Classifier: Programming Language :: Python :: 3.12
Requires-Dist: PyGObject (>=3.42.0,<4.0.0)
Requires-Dist: tomlkit (==0.*)
